bulge/__init__.py
bulge/tmp.py
bulge-0.0.1.dist-info/LICENSE
bulge-0.0.1.dist-info/METADATA
bulge-0.0.1.dist-info/WHEEL
bulge-0.0.1.dist-info/top_level.txt
bulge-0.0.1.dist-info/RECORD
